zompt/api/__init__.py
zompt/api/arrow_selection_prompt.py
zompt/api/input_prompt.py
zompt/api/prompt_helper.py
zompt/api/selector.py
zompt/run/__init__.py
zompt/run/runner.py
zompt-0.1.0.dist-info/LICENSE
zompt-0.1.0.dist-info/METADATA
zompt-0.1.0.dist-info/WHEEL
zompt-0.1.0.dist-info/top_level.txt
zompt-0.1.0.dist-info/RECORD
