Metadata-Version: 2.1
Name: zompt
Version: 0.1.0
Summary: Simple Python Prompt
Home-page: https://github.com/alexethier/zompt
Author: Alex Ethier
Author-email: aethier@gmail.com
License: MIT
Platform: UNKNOWN
Classifier: Development Status :: 1 - Planning
Classifier: License :: OSI Approved :: BSD License
Classifier: Operating System :: POSIX :: Linux
Classifier: Programming Language :: Python :: 3
Classifier: Programming Language :: Python :: 3.4
Classifier: Programming Language :: Python :: 3.5
License-File: LICENSE
Requires-Dist: zeys
